LICENSE
README.md
setup.py
pythreadpool/__init__.py
pythreadpool/gevent_thread_pool.py
pythreadpool/native_thread_pool.py
pythreadpool.egg-info/PKG-INFO
pythreadpool.egg-info/SOURCES.txt
pythreadpool.egg-info/dependency_links.txt
pythreadpool.egg-info/top_level.txt