Metadata-Version: 2.1
Name: pythreadpool
Version: 1.0.8
Summary: Thread pool for async jobs manage
Home-page: https://github.com/ChenZaichuang/pythreadpool
Author: ChenZaichuang
Author-email: 1158400735@qq.com
License: MIT Licence
Keywords: pip,pythreadpool,thread pool
Platform: any
License-File: LICENSE
